LICENSE
MANIFEST.in
README.md
requirements.txt
setup.cfg
setup.py
GridWalker.egg-info/PKG-INFO
GridWalker.egg-info/SOURCES.txt
GridWalker.egg-info/dependency_links.txt
GridWalker.egg-info/not-zip-safe
GridWalker.egg-info/requires.txt
GridWalker.egg-info/top_level.txt
gridwalker/__init__.py
gridwalker/grids.py