Metadata-Version: 1.1
Name: GridWalker
Version: 1.0.1
Summary: A multi-dimensional grid used for state space searching
Home-page: https://github.com/OpenGov/grid_walker
Author: Matthew Seal
Author-email: mseal@opengov.com
License: New BSD
Download-URL: https://github.com/OpenGov/grid_walker/tarball/v1.0.1
Keywords: grids,data,iterator,multi-dimensional
Platform: UNKNOWN
Classifier: Development Status :: 3 - Alpha
Classifier: Topic :: Utilities
Classifier: License :: OSI Approved :: BSD License
Classifier: Natural Language :: English
Classifier: Programming Language :: Python :: 2 :: Only
